AUTHORS
CHANGELOG
CONTRIBUTING.rst
LICENSE
MANIFEST.in
README.rst
VERSION
setup.py
transmutator/__init__.py
transmutator/api.py
transmutator/cli.py
transmutator/mutations.py
transmutator/orchestration.py
transmutator.egg-info/PKG-INFO
transmutator.egg-info/SOURCES.txt
transmutator.egg-info/dependency_links.txt
transmutator.egg-info/entry_points.txt
transmutator.egg-info/not-zip-safe
transmutator.egg-info/requires.txt
transmutator.egg-info/top_level.txt
transmutator/tests/__init__.py
transmutator/tests/cli.py