Metadata-Version: 1.1
Name: transmutator
Version: 0.1
Summary: General purpose migration framework (upgrades, downgrades).
Home-page: https://transmutator.readthedocs.org/
Author: Benoît Bryon
Author-email: benoit@marmelune.net
License: BSD
Keywords: migration evolution upgrade downgrade shell deployment
Platform: UNKNOWN
Classifier: License :: OSI Approved :: BSD License
Classifier: Development Status :: 1 - Planning
Classifier: Intended Audience :: Developers
Classifier: Programming Language :: Python :: 2.7
